gogoproto/gogo_pb2.py
pxapi-0.9.0.dist-info/METADATA
pxapi-0.9.0.dist-info/RECORD
pxapi-0.9.0.dist-info/WHEEL
pxapi/__init__.py
pxapi/client.py
pxapi/data.py
pxapi/errors.py
pxapi/proto/cloudapi_pb2.py
pxapi/proto/cloudapi_pb2_grpc.py
pxapi/proto/uuid_pb2.py
pxapi/proto/vis_pb2.py
pxapi/proto/vizier_types_pb2.py
pxapi/proto/vizierapi_pb2.py
pxapi/proto/vizierapi_pb2_grpc.py
pxapi/utils.py
python/google/protobuf/__init__.py
python/google/protobuf/any_pb2.py
python/google/protobuf/api_pb2.py
python/google/protobuf/compiler/__init__.py
python/google/protobuf/compiler/plugin_pb2.py
python/google/protobuf/descriptor.py
python/google/protobuf/descriptor_database.py
python/google/protobuf/descriptor_pb2.py
python/google/protobuf/descriptor_pool.py
python/google/protobuf/duration_pb2.py
python/google/protobuf/empty_pb2.py
python/google/protobuf/field_mask_pb2.py
python/google/protobuf/internal/__init__.py
python/google/protobuf/internal/_parameterized.py
python/google/protobuf/internal/api_implementation.py
python/google/protobuf/internal/builder.py
python/google/protobuf/internal/containers.py
python/google/protobuf/internal/decoder.py
python/google/protobuf/internal/descriptor_database_test.py
python/google/protobuf/internal/descriptor_pool_test.py
python/google/protobuf/internal/descriptor_test.py
python/google/protobuf/internal/encoder.py
python/google/protobuf/internal/enum_type_wrapper.py
python/google/protobuf/internal/extension_dict.py
python/google/protobuf/internal/generator_test.py
python/google/protobuf/internal/import_test.py
python/google/protobuf/internal/import_test_package/__init__.py
python/google/protobuf/internal/json_format_test.py
python/google/protobuf/internal/keywords_test.py
python/google/protobuf/internal/message_factory_test.py
python/google/protobuf/internal/message_listener.py
python/google/protobuf/internal/message_test.py
python/google/protobuf/internal/proto_builder_test.py
python/google/protobuf/internal/python_message.py
python/google/protobuf/internal/reflection_test.py
