Metadata-Version: 2.1
Name: pxapi
Author: The Pixie Maintainers
Author-email: maintainers@px.dev
License: Apache-2.0
Classifier: Programming Language :: Python :: 3
Classifier: Programming Language :: Python :: 3.9
Classifier: Programming Language :: Python :: 3.10
Classifier: Programming Language :: Python :: 3.11
Classifier: Programming Language :: Python :: 3.12
Classifier: Programming Language :: Python :: 3.13
Classifier: Operating System :: OS Independent
Classifier: License :: OSI Approved :: Apache Software License
Classifier: Typing :: Typed
Requires-Python: >=3.9, < 3.14
Requires-Dist: Authlib==1.5.1
Requires-Dist: grpcio==1.70.0
Requires-Dist: grpcio-tools==1.70.0
Requires-Dist: protobuf==5.29.3
Version: 0.9.0
